[{"longest": "Harry Potter and the Philosophers Stone - J.K. Rowling \n\n\n\n\n And Firenze", "proper_nouns": ["Four", "Harry", "Hermione", "The", "Malfoy", "Fang", "Potter", "Philosophers", "Stone", "J.K.", "Rowling", "And", "Firenze"], "most_common": "\u2019s", "total_refs": 121}, {"longest": "Harry Potter , \n the famous Harry Potter , their hero of two Quidditch \n matches", "proper_nouns": ["Harry", "Potter", "Mr.", "Quidditch", "Hagrid"], "most_common": "\u2019s", "total_refs": 337}, {"longest": "Professor McGonagall \u2019s", "proper_nouns": ["Professor", "McGonagall"], "most_common": "\u2019s", "total_refs": 31}, {"longest": "the Invisibility Cloak", "proper_nouns": ["Invisibility", "Cloak"], "most_common": "the", "total_refs": 2}, {"longest": "Neville \n", "proper_nouns": ["Neville"], "most_common": "\u2019s", "total_refs": 30}, {"longest": "Draco Malfoy", "proper_nouns": ["Malfoy", "Draco"], "most_common": "his", "total_refs": 11}, {"longest": "Norbert", "proper_nouns": ["Norbert"], "most_common": "Norbert", "total_refs": 2}, {"longest": "Mr. Filch", "proper_nouns": ["Filch", "Mr.", "Bane"], "most_common": "\u201c", "total_refs": 49}, {"longest": "the tallest Astronomy Tower , \n which was out - of - bounds except for classes", "proper_nouns": ["Astronomy", "Tower"], "most_common": "which", "total_refs": 2}, {"longest": "Hermione Granger", "proper_nouns": ["Hermione", "Granger"], "most_common": "she", "total_refs": 38}, {"longest": "the \n story", "most_common": "the", "total_refs": 2}, {"longest": "Miss Granger", "proper_nouns": ["Miss", "Granger"], "most_common": "you", "total_refs": 3}, {"longest": "Mr. \n Longbottom", "proper_nouns": ["Mr.", "Longbottom"], "most_common": "you", "total_refs": 2}, {"longest": "it", "proper_nouns": ["Rowling"], "most_common": "it", "total_refs": 2}, {"longest": "Gryffindor", "proper_nouns": ["Gryffindor"], "most_common": "Gryffindor", "total_refs": 6}, {"longest": "A hundred and fifty points lost .", "proper_nouns": ["A"], "most_common": "points", "total_refs": 2}, {"longest": "That", "most_common": "lost", "total_refs": 2}, {"longest": "this", "most_common": "this", "total_refs": 2}, {"longest": "Gryffindors passing the giant hourglasses \n that recorded the House points the next day", "proper_nouns": ["Gryffindors", "House"], "most_common": "they", "total_refs": 2}, {"longest": "the \n school", "most_common": "the", "total_refs": 5}, {"longest": "the House Cup", "proper_nouns": ["House", "Cup"], "most_common": "the", "total_refs": 2}, {"longest": "they", "most_common": "they", "total_refs": 3}, {"longest": "we", "proper_nouns": ["Slytherins"], "most_common": "we", "total_refs": 3}, {"longest": "Fred and George", "proper_nouns": ["Fred", "George"], "most_common": "they", "total_refs": 5}, {"longest": "Ron \u2019s", "proper_nouns": ["Only", "Ron", "Ronan"], "most_common": "\u2019s", "total_refs": 57}, {"longest": "that", "proper_nouns": ["Resign"], "most_common": "that", "total_refs": 3}, {"longest": "Wood", "proper_nouns": ["Wood"], "most_common": "Wood", "total_refs": 2}, {"longest": "the \n Quidditch team", "proper_nouns": ["Quidditch"], "most_common": "we", "total_refs": 4}, {"longest": "even Quidditch", "proper_nouns": ["Quidditch"], "most_common": "its", "total_refs": 2}, {"longest": "The rest of the \n team", "proper_nouns": ["Gryffindor", "The"], "most_common": "they", "total_refs": 4}, {"longest": "Ronan and Bane", "proper_nouns": ["Hermione", "Neville", "Harry", "Ronan", "Bane", "Malfoy", "Fang"], "most_common": "we", "total_refs": 13}, {"longest": "Harry Potter and the Philosophers Stone - J.K. Rowling", "proper_nouns": ["Harry", "Potter", "Philosophers", "Stone", "J.K.", "Rowling"], "most_common": "them", "total_refs": 5}, {"longest": "the Philosophers Stone - J.K. Rowling", "proper_nouns": ["Philosophers", "Stone", "J.K.", "Rowling"], "most_common": "the", "total_refs": 4}, {"longest": "He , Ron , and Hermione", "proper_nouns": ["Ron", "Hermione"], "most_common": "themselves", "total_refs": 2}, {"longest": "the exams", "most_common": "the", "total_refs": 2}, {"longest": "Quirrell \u2019s", "proper_nouns": ["Quirrell"], "most_common": "\u2019s", "total_refs": 13}, {"longest": "the \n classroom", "most_common": "the", "total_refs": 4}, {"longest": "a door", "most_common": "it", "total_refs": 2}, {"longest": "\n him", "proper_nouns": ["Snape"], "most_common": "his", "total_refs": 16}, {"longest": "the library , where Hermione was \n testing Ron on Astronomy", "proper_nouns": ["Hermione", "Ron", "Astronomy"], "most_common": "where", "total_refs": 4}, {"longest": "That", "proper_nouns": ["Go"], "most_common": "That", "total_refs": 2}, {"longest": "the troll", "most_common": "troll", "total_refs": 4}, {"longest": "Dumbledore", "proper_nouns": ["Dumbledore"], "most_common": "he", "total_refs": 5}, {"longest": "it", "most_common": "it", "total_refs": 2}, {"longest": "its", "proper_nouns": ["Jupiter"], "most_common": "its", "total_refs": 2}, {"longest": "They", "most_common": "notes", "total_refs": 2}, {"longest": "Harry , \n Hermione , and Neville", "proper_nouns": ["Harry", "Hermione", "Neville"], "most_common": "and", "total_refs": 2}, {"longest": "the entrance \n hall", "most_common": "the", "total_refs": 3}, {"longest": "Malfoy", "proper_nouns": ["Malfoy", "Yeh", "Yeh\u2019ve"], "most_common": "\u201d", "total_refs": 32}, {"longest": "the chains", "most_common": "\u2019em", "total_refs": 3}, {"longest": "their punishment", "most_common": "their", "total_refs": 2}, {"longest": "the moon", "proper_nouns": ["The"], "most_common": "the", "total_refs": 3}, {"longest": "Hagrid \u2019s", "proper_nouns": ["Hagrid"], "most_common": "\u2019s", "total_refs": 5}, {"longest": "this idiot", "proper_nouns": ["Longbottom"], "most_common": "this", "total_refs": 4}, {"longest": "it", "most_common": "it", "total_refs": 2}, {"longest": "the Philosophers Stone - J.K. Rowling", "proper_nouns": ["Philosophers", "Stone", "J.K.", "Rowling"], "most_common": "the", "total_refs": 3}, {"longest": "the \n forest", "proper_nouns": ["The"], "most_common": "this", "total_refs": 18}, {"longest": "ter", "most_common": "ter", "total_refs": 3}, {"longest": "it", "most_common": "wrong", "total_refs": 2}, {"longest": "it", "most_common": "this", "total_refs": 2}, {"longest": "this", "most_common": "this", "total_refs": 2}, {"longest": "my \n father", "most_common": "my", "total_refs": 2}, {"longest": "Hogwarts", "proper_nouns": ["Hogwarts"], "most_common": "Hogwarts", "total_refs": 2}, {"longest": "Copyin \u2019 lines !", "proper_nouns": ["Copyin"], "most_common": "\u2019", "total_refs": 2}, {"longest": "tonight", "most_common": "tonight", "total_refs": 5}, {"longest": "that stuff shinin \u2019 on \n the ground", "most_common": "\u2019", "total_refs": 2}, {"longest": "that \n thing you saved me from", "proper_nouns": ["The"], "most_common": "you", "total_refs": 12}, {"longest": "a narrow , winding \n earth track that disappeared into the thick black \n trees", "most_common": "winding", "total_refs": 11}, {"longest": "Fang \u2019s", "proper_nouns": ["Fang"], "most_common": "\u2019s", "total_refs": 10}, {"longest": "Harry , \n Hermione , and Hagrid", "proper_nouns": ["Harry", "Hermione\u2019ll", "Hermione", "Hagrid"], "most_common": "\u2019", "total_refs": 2}, {"longest": "a unicorn", "most_common": "unicorn", "total_refs": 2}, {"longest": "it", "most_common": "it", "total_refs": 2}, {"longest": "a towering oak", "proper_nouns": ["THAT", "TREE"], "most_common": "towering", "total_refs": 2}, {"longest": "an \n arrow", "most_common": "it", "total_refs": 3}, {"longest": "his \n crossbow", "most_common": "large", "total_refs": 5}, {"longest": "the sound", "most_common": "the", "total_refs": 6}, {"longest": "a clearing ahead", "most_common": "the", "total_refs": 5}, {"longest": "a horse \u2019s", "most_common": "\u2019s", "total_refs": 2}, {"longest": "Harry Potter an \u2019 Hermione Granger", "proper_nouns": ["Harry", "Potter", "Hermione", "Granger"], "most_common": "\u2019", "total_refs": 2}, {"longest": "you", "proper_nouns": ["Students"], "most_common": "you", "total_refs": 3}, {"longest": "Mars", "proper_nouns": ["Mars"], "most_common": "Mars", "total_refs": 3}, {"longest": "a unicorn \n bin injured", "most_common": "unicorn", "total_refs": 2}, {"longest": "yeh", "most_common": "you", "total_refs": 2}, {"longest": "they", "most_common": "they", "total_refs": 6}, {"longest": "jus \u2019 bin", "most_common": "\u2019", "total_refs": 2}, {"longest": "it", "most_common": "that", "total_refs": 2}, {"longest": "the others", "most_common": "the", "total_refs": 2}, {"longest": "Malfoy , \n Neville , and Fang", "proper_nouns": ["Malfoy", "Neville", "Fang"], "most_common": "and", "total_refs": 2}, {"longest": "Something bright white", "most_common": "white", "total_refs": 9}, {"longest": "the \n ground", "most_common": "the", "total_refs": 2}, {"longest": "The hooded figure", "proper_nouns": ["The"], "most_common": "the", "total_refs": 10}, {"longest": "the blood", "most_common": "the", "total_refs": 3}, {"longest": "its head", "most_common": "its", "total_refs": 2}, {"longest": "Harry \u2019s head", "proper_nouns": ["Harry"], "most_common": "\u2019s", "total_refs": 3}, {"longest": "The centaur", "proper_nouns": ["A", "The"], "most_common": "you", "total_refs": 16}, {"longest": "the scar that stood out , \n livid , on Harry \u2019s forehead", "proper_nouns": ["Harry"], "most_common": "\u2019s", "total_refs": 2}, {"longest": "Firenze \u2019s", "proper_nouns": ["Firenze"], "most_common": "\u2019s", "total_refs": 39}, {"longest": "our", "proper_nouns": ["Centaurs"], "most_common": "our", "total_refs": 3}, {"longest": "the planets", "most_common": "the", "total_refs": 2}, {"longest": "the dense , dark trees", "most_common": "trees", "total_refs": 3}, {"longest": "That", "most_common": "used", "total_refs": 2}, {"longest": "your", "most_common": "yourself", "total_refs": 3}, {"longest": "It", "most_common": "it", "total_refs": 3}, {"longest": "him", "most_common": "him", "total_refs": 3}, {"longest": "his back", "most_common": "his", "total_refs": 2}, {"longest": "the \n Stone", "proper_nouns": ["Stone"], "most_common": "the", "total_refs": 3}, {"longest": "Voldemort", "proper_nouns": ["Voldemort"], "most_common": "Voldemort", "total_refs": 6}, {"longest": "Bane", "proper_nouns": ["Bane"], "most_common": "Bane", "total_refs": 4}, {"longest": "the planets", "proper_nouns": ["The"], "most_common": "the", "total_refs": 3}, {"longest": "the Philosophers Stone", "proper_nouns": ["Philosophers", "Stone"], "most_common": "the", "total_refs": 2}, {"longest": "fortune - telling", "most_common": "that", "total_refs": 2}, {"longest": "his sheets", "most_common": "them", "total_refs": 2}, {"longest": "his \n Invisibility Cloak", "proper_nouns": ["Invisibility", "Cloak"], "most_common": "it", "total_refs": 2}]